Workbook

Sheet Comparison
A1: Handled Services LLC: Invoice Factoring Comparison
A2: FILE: docs/FACTORING_COMPARISON_2026-10-06_0320.xlsx | CREATED: 2026-10-06_0320 UTC | PROJECT: Handled (myhumanai)
A3: PURPOSE: Compare 5 factoring companies so weekly pro payouts are covered while business, city and government clients pay on net 30+.
A4: LEGEND: yellow cells = fill in from each company's quote. Blue text = typed facts from public websites (verify on the call). Fee % per 30 days is stored as a fraction (0.015 = 1.5%).
A6: Company | B6: Website | C6: Why it fits Handled | D6: Gov invoices (Fed / State / City) | E6: Advance rate (quote) | F6: Fee % per 30 days (quote) | G6: Days to first funding | H6: Recourse or non-recourse | I6: Monthly minimum volume | J6: Contract term / early-exit fee | K6: Spot factoring allowed? | L6: Other fees (setup, ACH, credit checks) | M6: Contact name / phone / email | N6: Date contacted | O6: Status | P6: Notes
A7: Advance Partners | B7: advancepartners.com/payroll-funding/government-staffing/ | C7: Payroll funding for staffing on government contracts (incl. municipal); back office for payroll and billing. Best fit for weekly pro payouts. | O7: Not contacted
A8: 1st Commercial Credit | B8: 1stcommercialcredit.com/financial-services/government-receivables | C8: Dedicated government-receivables program plus staffing/payroll funding; works with small businesses. | O8: Not contacted
A9: Porter Capital | B9: portercap.com/government-invoice-factoring | C9: Long-time government contractor factoring; covers service and staffing businesses. | O9: Not contacted
A10: eCapital | B10: ecapital.com | C10: Large lender with government contractor financing; can grow into an asset-based credit line for bigger contracts. | O10: Not contacted
A11: 8A Factoring | B11: 8afactoring.com | C11: Government invoices for small and 8(a)/minority-owned businesses; fits set-aside, MBE/DBE work. | O11: Not contacted
A12: Example row (format only, not a real quote):
A13: Sample Factor Co. | B13: example.com | C13: Example of how to fill a row | D13: Fed + City | E13: 0.85 | F13: 0.015 | G13: 2 | H13: Recourse | I13: $25,000 | J13: 12 mo / 3% exit | K13: Yes | L13: $300 setup | M13: J. Smith 313-555-0100 | O13: Quote received | P13: Rate drops to 1.2% above $100K/mo
A15: Market reference: advances typically 80-90%; government receivables about 0.69%-1.59% per 30 days (United Capital Source). Net-30 invoices cost less to factor than net-60/90.

Sheet Cost Calculator
A1: Handled Services LLC: Factoring Cost Calculator
A2: FILE: docs/FACTORING_COMPARISON_2026-10-06_0320.xlsx | CREATED: 2026-10-06_0320 UTC | PROJECT: Handled (myhumanai)
A3: PURPOSE: Compare total cost on the same sample invoice once quotes come in.
A4: LEGEND: yellow = inputs you can change. Green = pulled from the Comparison tab. Black = formulas.
A6: Sample invoice amount ($) | B6: 50000 | C6: Assumption: placeholder. Use a real invoice from a current client.
A7: Days until client pays | B7: 30 | C7: Net 30 = 30. Cities often pay in 45-60.
A8: Fee billing increment (days) | B8: 30 | C8: Most factors charge per 30 days (some per 10 or 15). Confirm with each.
A9: Flat fees per invoice ($) | B9: 0 | C9: Add any per-invoice ACH or processing fees.
A11: Company | B11: Advance rate | C11: Fee % per period | D11: Fee periods | E11: Cash up front ($) | F11: Factoring fee ($) | G11: Total cost ($) | H11: Cost as % of invoice | I11: Effective annual rate | J11: Rebate when client pays ($)
A12: =Comparison!A7 -> Advance Partners | B12: =IF(Comparison!E7="","",Comparison!E7) | C12: =IF(Comparison!F7="","",Comparison!F7) | D12: =IF($B$8>0,CEILING($B$7/$B$8,1),0) -> 1 | E12: =IF(OR(B12="",C12=""),"Awaiting quote",$B$6*B12) -> Awaiting quote | F12: =IF(OR(B12="",C12=""),"Awaiting quote",$B$6*C12*D12) -> Awaiting quote | G12: =IF(OR(B12="",C12=""),"Awaiting quote",F12+$B$9) -> Awaiting quote | H12: =IF(OR(OR(B12="",C12=""),$B$6=0),"",G12/$B$6) | I12: =IF(OR(OR(B12="",C12=""),$B$7=0,B12=0),"",(G12/E12)*(365/$B$7)) | J12: =IF(OR(B12="",C12=""),"Awaiting quote",$B$6-E12-G12) -> Awaiting quote
A13: =Comparison!A8 -> 1st Commercial Credit | B13: =IF(Comparison!E8="","",Comparison!E8) | C13: =IF(Comparison!F8="","",Comparison!F8) | D13: =IF($B$8>0,CEILING($B$7/$B$8,1),0) -> 1 | E13: =IF(OR(B13="",C13=""),"Awaiting quote",$B$6*B13) -> Awaiting quote | F13: =IF(OR(B13="",C13=""),"Awaiting quote",$B$6*C13*D13) -> Awaiting quote | G13: =IF(OR(B13="",C13=""),"Awaiting quote",F13+$B$9) -> Awaiting quote | H13: =IF(OR(OR(B13="",C13=""),$B$6=0),"",G13/$B$6) | I13: =IF(OR(OR(B13="",C13=""),$B$7=0,B13=0),"",(G13/E13)*(365/$B$7)) | J13: =IF(OR(B13="",C13=""),"Awaiting quote",$B$6-E13-G13) -> Awaiting quote
A14: =Comparison!A9 -> Porter Capital | B14: =IF(Comparison!E9="","",Comparison!E9) | C14: =IF(Comparison!F9="","",Comparison!F9) | D14: =IF($B$8>0,CEILING($B$7/$B$8,1),0) -> 1 | E14: =IF(OR(B14="",C14=""),"Awaiting quote",$B$6*B14) -> Awaiting quote | F14: =IF(OR(B14="",C14=""),"Awaiting quote",$B$6*C14*D14) -> Awaiting quote | G14: =IF(OR(B14="",C14=""),"Awaiting quote",F14+$B$9) -> Awaiting quote | H14: =IF(OR(OR(B14="",C14=""),$B$6=0),"",G14/$B$6) | I14: =IF(OR(OR(B14="",C14=""),$B$7=0,B14=0),"",(G14/E14)*(365/$B$7)) | J14: =IF(OR(B14="",C14=""),"Awaiting quote",$B$6-E14-G14) -> Awaiting quote
A15: =Comparison!A10 -> eCapital | B15: =IF(Comparison!E10="","",Comparison!E10) | C15: =IF(Comparison!F10="","",Comparison!F10) | D15: =IF($B$8>0,CEILING($B$7/$B$8,1),0) -> 1 | E15: =IF(OR(B15="",C15=""),"Awaiting quote",$B$6*B15) -> Awaiting quote | F15: =IF(OR(B15="",C15=""),"Awaiting quote",$B$6*C15*D15) -> Awaiting quote | G15: =IF(OR(B15="",C15=""),"Awaiting quote",F15+$B$9) -> Awaiting quote | H15: =IF(OR(OR(B15="",C15=""),$B$6=0),"",G15/$B$6) | I15: =IF(OR(OR(B15="",C15=""),$B$7=0,B15=0),"",(G15/E15)*(365/$B$7)) | J15: =IF(OR(B15="",C15=""),"Awaiting quote",$B$6-E15-G15) -> Awaiting quote
A16: =Comparison!A11 -> 8A Factoring | B16: =IF(Comparison!E11="","",Comparison!E11) | C16: =IF(Comparison!F11="","",Comparison!F11) | D16: =IF($B$8>0,CEILING($B$7/$B$8,1),0) -> 1 | E16: =IF(OR(B16="",C16=""),"Awaiting quote",$B$6*B16) -> Awaiting quote | F16: =IF(OR(B16="",C16=""),"Awaiting quote",$B$6*C16*D16) -> Awaiting quote | G16: =IF(OR(B16="",C16=""),"Awaiting quote",F16+$B$9) -> Awaiting quote | H16: =IF(OR(OR(B16="",C16=""),$B$6=0),"",G16/$B$6) | I16: =IF(OR(OR(B16="",C16=""),$B$7=0,B16=0),"",(G16/E16)*(365/$B$7)) | J16: =IF(OR(B16="",C16=""),"Awaiting quote",$B$6-E16-G16) -> Awaiting quote
A18: Example (85% / 1.5%) | B18: 0.85 | C18: 0.015 | D18: =IF($B$8>0,CEILING($B$7/$B$8,1),0) -> 1 | E18: =$B$6*B18 -> 42500 | F18: =$B$6*C18*D18 -> 750 | G18: =F18+$B$9 -> 750 | H18: =IF($B$6=0,"",G18/$B$6) -> 0.015 | I18: =IF(OR($B$7=0,E18=0),"",(G18/E18)*(365/$B$7)) -> 0.21470588 | J18: =$B$6-E18-G18 -> 6750
A20: How to read it: 'Cash up front' is what lands in the bank in 1-2 days and covers that week's pro payouts. 'Rebate' is the rest, paid after the client pays the factor. 'Effective annual rate' compares factoring with a bank line of credit.
A21: Example row uses typical market terms (85% advance, 1.5% per 30 days) for illustration only; it is not a quote.

Sheet Questions & Gov Rules
A1: Handled Services LLC: Questions to Ask & Government Rules
A2: FILE: docs/FACTORING_COMPARISON_2026-10-06_0320.xlsx | CREATED: 2026-10-06_0320 UTC | PROJECT: Handled (myhumanai)
A3: PURPOSE: Ask every factor the same questions so the quotes compare cleanly.
A5: # | B5: Question / rule | C5: Why it matters
A6: Ask | B6: What is the advance rate and the fee per 30 days (or per 10/15 days)? | C6: Drives the Cost Calculator. Get it in writing.
A7: Ask | B7: Recourse or non-recourse? If non-recourse, what does it cover (client bankruptcy only)? | C7: With recourse, Handled buys back invoices the client never pays.
A8: Ask | B8: Is there a monthly minimum volume, and a fee if we fall below it? | C8: Minimums punish slow months while we grow.
A9: Ask | B9: How long is the contract, does it auto-renew, and what is the early-termination fee? | C9: Avoid 12-24 month lock-ins with large exit fees.
A10: Ask | B10: Can we choose which invoices or clients to factor (spot / selective factoring)? | C10: Factor only slow payers (cities, large businesses); keep fast payers unfactored.
A11: Ask | B11: All other fees: setup, due diligence, ACH/wire, credit checks, lockbox, invoice processing? | C11: Small fees can double the real cost.
A12: Ask | B12: Do you fund federal, State of Michigan and City of Detroit / municipal invoices? Any you won't fund? | C12: Some factors avoid municipal or state receivables.
A13: Ask | B13: Do you need a UCC-1 lien on all receivables or only factored invoices? | C13: A blanket lien can block a future bank loan.
A14: Ask | B14: Can you fund the same day an invoice is approved by the client, to match our weekly pro payout run? | C14: The whole point is covering weekly payouts.
A15: Ask | B15: Will you contact our clients? How (notification letter, collections calls)? | C15: Protect client relationships, especially with city buyers.
A16: Rule | B16: Federal contracts: an Assignment of Claims (Assignment of Claims Act / FAR 32.8) must be filed with the contracting officer and disbursing office. | C16: Without it the agency will not pay the factor.
... A19: Rule | B19: Service Contract Act / Davis-Bacon wage rules still apply to factored contracts. | C19: Factoring changes when we get paid, not what we owe workers.

Sheet Sources
A1: Handled Services LLC: Sources
A2: FILE: docs/FACTORING_COMPARISON_2026-10-06_0320.xlsx | CREATED: 2026-10-06_0320 UTC | PROJECT: Handled (myhumanai)
A3: PURPOSE: Where the company facts and market ranges came from (web search, 2026-10-06). Verify on each call.
A5: Source | B5: URL
A6: Advance Partners: Government staffing payroll funding | B6: https://www.advancepartners.com/payroll-funding/government-staffing/
A7: 1st Commercial Credit: Government receivables | B7: https://www.1stcommercialcredit.com/financial-services/government-receivables
A8: 1st Commercial Credit: Payroll funding for staffing | B8: https://www.1stcommercialcredit.com/blog/payroll-funding-staffing-agencies
A9: Porter Capital: Government invoice factoring | B9: https://portercap.com/government-invoice-factoring
A10: eCapital: Government contractor financing | B10: https://ecapital.com/blog/using-government-contractor-financing-to-bridge-cash-flow-gaps
A11: 8A Factoring (brand profile) | B11: https://www.parse.gl/brands/8afactoring-com
A12: United Capital Source: Government receivables rates (0.69%-1.59%) | B12: https://www.unitedcapitalsource.com/?p=132379
A13: Summar: Funding weekly payroll on net-30 terms | B13: https://summar.com/?p=31563
